cznic_auctions/__init__.py
cznic_auctions/cms_plugins.py
cznic_auctions/constants.py
cznic_auctions/loader.py
cznic_auctions/models.py
cznic_auctions/urls.py
cznic_auctions/views.py
cznic_auctions/locale/cs/LC_MESSAGES/django.mo
cznic_auctions/locale/cs/LC_MESSAGES/django.po
cznic_auctions/migrations/0001_initial.py
cznic_auctions/migrations/0002_auctionslist_sort_by.py
cznic_auctions/migrations/0003_auctionslist_template.py
cznic_auctions/migrations/0004_alter_auctionslist_template.py
cznic_auctions/migrations/0005_auctions_label_alter_auctionslist_template.py
cznic_auctions/migrations/0006_auctionslist_context_alter_auctionslist_template.py
cznic_auctions/migrations/__init__.py
cznic_auctions/static/cznic_auctions/img/unwatch.svg
cznic_auctions/templates/cznic_auctions/export-csv.html
cznic_auctions/templates/cznic_auctions/list.html
cznic_auctions/templates/cznic_auctions/list_bids_price.html
cznic_auctions/templates/cznic_auctions/total.html
cznic_auctions/tests/__init__.py
cznic_auctions/tests/settings.py
cznic_auctions/tests/test_auctions_loader.py
cznic_auctions/tests/test_auctions_models.py
cznic_auctions/tests/test_auctions_plugins.py
cznic_auctions/tests/test_auctions_views.py
cznic_auctions/tests/urls.py
cznic_auctions/tests/templates/page.html
djangocms_cznic_auctions-1.4.0.dist-info/METADATA
djangocms_cznic_auctions-1.4.0.dist-info/WHEEL
djangocms_cznic_auctions-1.4.0.dist-info/top_level.txt
djangocms_cznic_auctions-1.4.0.dist-info/RECORD
